simple_lib_test/__init__.py
simple_lib_test/simple_lib_test.py
simple_lib_test-0.5.dist-info/METADATA
simple_lib_test-0.5.dist-info/WHEEL
simple_lib_test-0.5.dist-info/top_level.txt
simple_lib_test-0.5.dist-info/RECORD
