Metadata-Version: 2.1
Name: simple-lib-test
Version: 0.5
Summary: A simple library to get numbers from 1 to 6
Author: Yash Varma
Author-email: varmayash150@gmail.com
